parliament/__init__.py
parliament/cli.py
parliament/config.yaml
parliament/finding.py
parliament/iam_definition.json
parliament/misc.py
parliament/policy.py
parliament/statement.py
parliament/community_auditors/__init__.py
parliament/community_auditors/advanced_policy_elements.py
parliament/community_auditors/config_override.yaml
parliament/community_auditors/credentials_exposure.py
parliament/community_auditors/permissions_management.py
parliament/community_auditors/privilege_escalation.py
parliament/community_auditors/sensitive_access.py
parliament/community_auditors/single_value_condition_too_permissive.py
parliament-1.6.4.dist-info/licenses/LICENSE
parliament-1.6.4.dist-info/METADATA
parliament-1.6.4.dist-info/WHEEL
parliament-1.6.4.dist-info/entry_points.txt
parliament-1.6.4.dist-info/top_level.txt
parliament-1.6.4.dist-info/zip-safe
parliament-1.6.4.dist-info/RECORD
