Metadata-Version: 2.4
Name: parliament
Version: 1.6.4
Summary: parliament audits your AWS IAM policies
Home-page: https://github.com/duo-labs/parliament
Author: Duo Security
Author-email: scott@summitroute.com
License: BSD 3
Keywords: aws parliament iam lint audit
Classifier: License :: OSI Approved :: BSD License
Classifier: Programming Language :: Python :: 3
Classifier: Programming Language :: Python :: 3.6
Classifier: Programming Language :: Python :: 3.7
Classifier: Programming Language :: Python :: 3.8
Classifier: Programming Language :: Python :: 3 :: Only
Classifier: Development Status :: 5 - Production/Stable
Requires-Python: >=3.6
License-File: LICENSE
Requires-Dist: boto3
Requires-Dist: jmespath
Requires-Dist: pyyaml
Requires-Dist: json-cfg
Provides-Extra: dev
Requires-Dist: coverage; extra == "dev"
Requires-Dist: nose; extra == "dev"
Requires-Dist: autoflake; extra == "dev"
Requires-Dist: autopep8; extra == "dev"
Requires-Dist: pylint; extra == "dev"
Dynamic: author
Dynamic: author-email
Dynamic: classifier
Dynamic: description
Dynamic: description-content-type
Dynamic: home-page
Dynamic: keywords
Dynamic: license
Dynamic: license-file
Dynamic: provides-extra
Dynamic: requires-dist
Dynamic: requires-python
Dynamic: summary
